chekml/__init__.py
chekml/MetaheuristicOptimization/benchmark.py
chekml/MetaheuristicOptimization/benchmark_NoVerbose.py
chekml/MetaheuristicOptimization/CIntegration_cffi/__init__.py
chekml/MetaheuristicOptimization/CIntegration_cffi/benchmark.py
chekml/MetaheuristicOptimization/CIntegration_cffi/fine_tune.py
chekml/MetaheuristicOptimization/CIntegration_cffi/generaloptimizer.so
chekml/MetaheuristicOptimization/CIntegration_cffi/wrapper.py
chekml/MetaheuristicOptimization/CIntegration_cffi/wrapper2.py
chekml/MetaheuristicOptimization/CIntegration_cffi1/__init__.py
chekml/MetaheuristicOptimization/CIntegration_cffi1/benchmark.py
chekml/MetaheuristicOptimization/CIntegration_cffi1/diso_finetune.py
chekml/MetaheuristicOptimization/CIntegration_cffi1/generaloptimizer.so
chekml/MetaheuristicOptimization/CIntegration_cffi1/wrapper.py
chekml/MetaheuristicOptimization/CIntegration_cffi2/__init__.py
chekml/MetaheuristicOptimization/CIntegration_cffi2/benchmark.py
chekml/MetaheuristicOptimization/CIntegration_cffi2/diso_finetune.py
chekml/MetaheuristicOptimization/CIntegration_cffi2/generaloptimizer.so
chekml/MetaheuristicOptimization/CIntegration_cffi2/wrapper.py
chekml/MetaheuristicOptimization/CIntegration_cffi2/wrapper2.py
chekml/MetaheuristicOptimization/CIntegration_cffi3/__init__.py
chekml/MetaheuristicOptimization/CIntegration_cffi3/benchmark.py
chekml/MetaheuristicOptimization/CIntegration_cffi3/diso_finetune.py
chekml/MetaheuristicOptimization/CIntegration_cffi3/generaloptimizer.so
chekml/MetaheuristicOptimization/CIntegration_cffi3/wrapper.py
chekml/MetaheuristicOptimization/CIntegration_cffi3/wrapper2.py
chekml/MetaheuristicOptimization/CIntegration_ctypes/DISOwithRCF.so
chekml/MetaheuristicOptimization/CIntegration_ctypes/GPC.so
chekml/MetaheuristicOptimization/CIntegration_ctypes/__init__.py
chekml/MetaheuristicOptimization/CIntegration_ctypes/benchmark.py
chekml/MetaheuristicOptimization/CIntegration_ctypes/diso_wrapper.py
chekml-0.1.18.dist-info/licenses/LICENSE
chekml-0.1.18.dist-info/METADATA
chekml-0.1.18.dist-info/WHEEL
chekml-0.1.18.dist-info/top_level.txt
chekml-0.1.18.dist-info/RECORD
