Metadata-Version: 2.4
Name: chekml
Version: 0.1.18
Summary: A versatile library for data manipulation
Author-email: Chek Chee Him <cchgolden050@gmail.com>
License-Expression: MIT
Requires-Python: >=3.7
License-File: LICENSE
Dynamic: license-file
